yta_math_progression/__init__.py
yta_math_progression-0.0.4.dist-info/licenses/LICENSE
yta_math_progression-0.0.4.dist-info/METADATA
yta_math_progression-0.0.4.dist-info/WHEEL
yta_math_progression-0.0.4.dist-info/RECORD
