Metadata-Version: 2.4
Name: yta-math-progression
Version: 0.0.4
Summary: Youtube Autonomous Math Progression Module.
License-File: LICENSE
Author: danialcala94
Author-email: danielalcalavalera@gmail.com
Requires-Python: ==3.9
Classifier: Programming Language :: Python :: 3
Classifier: Programming Language :: Python :: 3.9
Requires-Dist: numpy (>=1.22.0,<3.0.0)
Requires-Dist: yta_math_easings (>=0.0.1,<1.0.0)
Requires-Dist: yta_math_normalization (>=0.0.1,<1.0.0)
Requires-Dist: yta_validation (>=0.0.1,<1.0.0)
